channels_redis/__init__.py
channels_redis/core.py
channels_redis/pubsub.py
channels_redis/utils.py
channels_redis-4.2.0.dist-info/LICENSE
channels_redis-4.2.0.dist-info/METADATA
channels_redis-4.2.0.dist-info/WHEEL
channels_redis-4.2.0.dist-info/top_level.txt
channels_redis-4.2.0.dist-info/RECORD
