Metadata-Version: 2.1
Name: channels_redis
Version: 4.2.0
Summary: Redis-backed ASGI channel layer implementation
Home-page: http://github.com/django/channels_redis/
Author: Django Software Foundation
Author-email: foundation@djangoproject.com
License: BSD
Requires-Python: >=3.8
Provides-Extra: cryptography
Provides-Extra: tests
License-File: LICENSE
